amandas_rerp_ols/__init__.py
amandas_rerp_ols/my_method.py
amandas_rerp_ols-0.0.3.dist-info/LICENSE.txt
amandas_rerp_ols-0.0.3.dist-info/METADATA
amandas_rerp_ols-0.0.3.dist-info/WHEEL
amandas_rerp_ols-0.0.3.dist-info/top_level.txt
amandas_rerp_ols-0.0.3.dist-info/RECORD
