Metadata-Version: 2.1
Name: amandas_rerp_ols
Version: 0.0.3
Summary: Packaging testing
Author-email: Amanda Lin <amanda.lin@gmail.com>
Project-URL: Homepage, https://github.com/amandalin047/StatsTools
Project-URL: Bug Tracker, https://github.com/amandalin047/StatsTools/issues
Classifier: Programming Language :: Python :: 3
Classifier: License :: OSI Approved :: MIT License
Classifier: Operating System :: OS Independent
Requires-Python: >=3.7
License-File: LICENSE.txt
